<?xml version="1.0" encoding="utf-8"?>
<form>
	<fields name="fieldparams">
		<fieldset name="fieldparams">
			<field
				name="query"
				type="textarea"
				filter="raw"
				label="PLG_FIELDS_SQL_PARAMS_QUERY_LABEL"
				description="PLG_FIELDS_SQL_PARAMS_QUERY_DESC"
				rows="10"
				required="true"
			/>

			<field
				name="multiple"
				type="list"
				label="PLG_FIELDS_SQL_PARAMS_MULTIPLE_LABEL"
				description="PLG_FIELDS_SQL_PARAMS_MULTIPLE_DESC"
			>
				<option value="">PLG_FIELDS_SQL_PARAMS_USE_GLOBAL</option>
				<option value="1">JYES</option>
				<option value="0">JNO</option>
			</field>
		</fieldset>
	</fields>
</form>
