<?xml version="1.0" encoding="utf-8"?>
<extension type="plugin" group="system" method="upgrade">
	<name>plg_system_highlight</name>
	<author>Joomla! Project</author>
	<creationDate>2011-08</creationDate>
	<copyright>(C) 2011 Open Source Matters, Inc.</copyright>
	<license>GNU General Public License version 2 or later; see	LICENSE.txt</license>
	<authorEmail>admin@joomla.org</authorEmail>
	<authorUrl>www.joomla.org</authorUrl>
	<version>3.0.0</version>
	<description>PLG_SYSTEM_HIGHLIGHT_XML_DESCRIPTION</description>
	<files>
		<filename plugin="highlight">highlight.php</filename>
	</files>
	<languages>
		<language tag="en-GB">language/en-GB/plg_system_highlight.ini</language>
		<language tag="en-GB">language/en-GB/plg_system_highlight.sys.ini</language>
	</languages>
</extension>
