<?xml version="1.0" encoding="utf-8"?>
<extension version="3.1" type="plugin" group="user" method="upgrade">
	<name>plg_user_contactcreator</name>
	<author>Joomla! Project</author>
	<creationDate>August 2009</creationDate>
	<copyright>(C) 2005 - 2016 Open Source Matters. All rights reserved.</copyright>
	<license>GNU General Public License version 2 or later; see LICENSE.txt</license>
	<authorEmail>admin@joomla.org</authorEmail>
	<authorUrl>www.joomla.org</authorUrl>
	<version>3.0.0</version>
	<description>PLG_CONTACTCREATOR_XML_DESCRIPTION</description>
	<files>
		<filename plugin="contactcreator">contactcreator.php</filename>
	</files>
	<languages>
		<language tag="en-GB">en-GB.plg_user_contactcreator.ini</language>
		<language tag="en-GB">en-GB.plg_user_contactcreator.sys.ini</language>
	</languages>
	<config>
		<fields name="params">
			<fieldset name="basic">
				<field name="autowebpage"
					type="text"
					size="40"
					description="PLG_CONTACTCREATOR_FIELD_AUTOMATIC_WEBPAGE_DESC"
					label="PLG_CONTACTCREATOR_FIELD_AUTOMATIC_WEBPAGE_LABEL"
				/>

				<field name="category"
					type="category"
					description="PLG_CONTACTCREATOR_FIELD_CATEGORY_DESC"
					extension="com_contact"
					label="JCATEGORY"
				/>

				<field name="autopublish"
					type="radio"
					class="btn-group btn-group-yesno"
					default="0"
					description="PLG_CONTACTCREATOR_FIELD_AUTOPUBLISH_DESC"
					label="PLG_CONTACTCREATOR_FIELD_AUTOPUBLISH_LABEL"
				>
					<option value="1">JYES</option>
					<option value="0">JNO</option>
				</field>
			</fieldset>
		</fields>
	</config>
</extension>
