<?xml version="1.0" encoding="utf8"?>
<metadata>
	<control>
		<steps>
			<step id="1" name="View">
				<message>
					<![CDATA[Choose the content component view.]]>
				</message>
				<params>
					<views name="view" directory="/components/com_content/views" />
				</params>
			</step>
			<include source="/components/com_content/views/{view}/metadata.xml" path="control/steps" />
		</steps>
	</control>
	<state>
		<include source="/components/com_content/views/{view}/tmpl/{template}.xml" path="state" />
	</state>
</metadata>