<?xml version="1.0" encoding="utf-8"?>
<metadata>
	<layout title="COM_NEWSFEEDS_CATEGORIES_VIEW_DEFAULT_TITLE">
		<help
			key = "JHELP_MENUS_MENU_ITEM_NEWSFEED_CATEGORIES"
		/>
		<message>
			<![CDATA[COM_NEWSFEEDS_CATEGORIES_VIEW_DEFAULT_DESC]]>
		</message>
	</layout>

	<!-- Add fields to the request variables for the layout. -->
	<fields name="request">
		<fieldset name="request"
		>
			<field name="id" type="category"
				description="JGLOBAL_FIELD_CATEGORIES_CHOOSE_CATEGORY_DESC"
				extension="com_newsfeeds"
				label="JGLOBAL_FIELD_CATEGORIES_CHOOSE_CATEGORY_LABEL"
				show_root="true"
				required="true"
			/>
		</fieldset>
	</fields>

	<!-- Add fields to the parameters object for the layout. -->
<fields name="params">
<fieldset name="basic" label="JGLOBAL_CATEGORY_OPTIONS">
			<field name="show_base_description" type="radio"
				label="JGLOBAL_FIELD_SHOW_BASE_DESCRIPTION_LABEL"
				description="JGLOBAL_FIELD_SHOW_BASE_DESCRIPTION_DESC"
				default="1"
			>
				<option value="0">JHIDE</option>
				<option value="1">JSHOW</option>
			</field>
			
			<field name="categories_description" type="textarea"
				description="JGLOBAL_FIELD_CATEGORIES_DESC_DESC"
				label="JGLOBAL_FIELD_CATEGORIES_DESC_LABEL"
				cols="25"
				rows="5"
			/>
			<field name="maxLevel" type="list"
				description="JGLOBAL_MAXIMUM_CATEGORY_LEVELS_DESC"
				label="JGLOBAL_MAXIMUM_CATEGORY_LEVELS_LABEL"
				default="-1"
			>
				<option value="-1">JALL</option>
				<option value="1">J1</option>
				<option value="2">J2</option>
				<option value="3">J3</option>
				<option value="4">J4</option>
				<option value="5">J5</option>
			</field>

			<field name="show_empty_categories" type="radio"
				label="COM_NEWSFEEDS_FIELD_SHOW_CATEGORY_EMPTY_LABEL"
				description="COM_NEWSFEEDS_FIELD_SHOW_CATEGORY_EMPTY_DESC"
				default="0"
			>
				<option value="0">JHIDE</option>
				<option value="1">JSHOW</option>
			</field>
			
			<field name="show_subcat_desc" type="radio"
			label="COM_NEWSFEEDS_FIELD_SHOW_CATEGORY_SUBCAT_LABEL"
			description="COM_NEWSFEEDS_FIELD_SHOW_CATEGORY_SUBCAT_DESC"
			default="0"
			>
				<option value="0">JHIDE</option>
				<option value="1">JSHOW</option>
			</field>
		
			<field name="show_cat_items" type="radio"
				label="COM_NEWSFEEDS_FIELD_SHOW_CAT_ITEMS_LABEL"
				description="COM_NEWSFEEDS_FIELD_SHOW_CAT_ITEMS_DESC"
				default="0"
			>
				<option value="0">JHIDE</option>
				<option value="1">JSHOW</option>
			</field>
	</fieldset>
	
</fields>
</metadata>