<?xml version="1.0" encoding="iso-8859-1"?>
<install version="1.5" type="template">
	<name>beez</name>
	<version>1.0.0</version>
	<creationDate>19 February 2007</creationDate>
	<author>Angie Radtke/Robert Deutz</author>
	<authorEmail>joomla@run-digital.com</authorEmail>
	<authorUrl>http://www.run-digital.com</authorUrl>
	<copyright></copyright>
	<license>GNU/GPL</license>
	<description>Accessible template for Joomla 1.5</description>
	<files>
		<filename>css/layout.css</filename>
		<filename>css/position.css</filename>
		<filename>css/template.css</filename>
		<filename>css/ieonly.css</filename>
		<filename>css/ie7only.css</filename>
		<filename>css/print.css</filename>
		<filename>css/index.html</filename>
		<filename>html/com_contact/category/default.php</filename>
		<filename>html/com_contact/category/default_items.php</filename>
		<filename>html/com_contact/category/index.html</filename>
		<filename>html/com_contact/contact/default.php</filename>
		<filename>html/com_contact/contact/default_address.php</filename>
		<filename>html/com_contact/contact/default_form.php</filename>
		<filename>html/com_contact/contact/index.html</filename>
		<filename>html/com_contact/index.html</filename>
		<filename>html/com_content/article/default.php</filename>
		<filename>html/com_content/article/index.html</filename>
		<filename>html/com_content/category/blog.php</filename>
		<filename>html/com_content/category/blog_item.php</filename>
		<filename>html/com_content/category/blog_links.php</filename>
		<filename>html/com_content/category/index.html</filename>
		<filename>html/com_content/category/default_items.php</filename>
		<filename>html/com_content/category/default.php</filename>
		<filename>html/com_content/frontpage/default.php</filename>
		<filename>html/com_content/frontpage/default_item.php</filename>
		<filename>html/com_content/frontpage/default_links.php</filename>
		<filename>html/com_content/frontpage/index.html</filename>
		<filename>html/com_content/section/blog.php</filename>
		<filename>html/com_content/section/blog_item.php</filename>
		<filename>html/com_content/section/blog_links.php</filename>
		<filename>html/com_content/section/default.php</filename>
		<filename>html/com_content/section/index.html</filename>
		<filename>html/com_content/index.html</filename>
		<filename>html/index.html</filename>
		<filename>html/com_search/search/default.php</filename>
		<filename>html/com_search/search/default_error.php</filename>
		<filename>html/com_search/search/default_form.php</filename>
		<filename>html/com_search/search/default_results.php</filename>
		<filename>html/com_search/search/index.html</filename>
		<filename>html/com_search/index.html</filename>
		<filename>html/editor_content.css</filename>
		<filename>html/mod_latestnews/default.php</filename>
		<filename>html/mod_latestnews/index.html</filename>
		<filename>html/mod_login/default.php</filename>
		<filename>html/mod_login/index.html</filename>
		<filename>html/mod_newsflash/_item.php</filename>
		<filename>html/mod_newsflash/default.php</filename>
		<filename>html/mod_newsflash/horiz.php</filename>
		<filename>html/mod_newsflash/vert.php</filename>
		<filename>html/mod_newsflash/index.html</filename>
		<filename>html/mod_poll/default.php</filename>
		<filename>html/mod_poll/index.html</filename>
		<filename>html/mod_search/default.php</filename>
		<filename>html/mod_search/index.html</filename>
		<filename>html/modules.php</filename>
		<filename>html/pagination.php</filename>
		<filename>html/com_poll/poll/default.php</filename>
		<filename>html/com_poll/poll/default_graph.php</filename>
		<filename>html/com_poll/poll/index.html</filename>
		<filename>html/com_poll/index.html</filename>
		<filename>html/com_newsfeeds/categories/default.php</filename>
		<filename>html/com_newsfeeds/categories/index.html</filename>
		<filename>html/com_newsfeeds/category/default.php</filename>
		<filename>html/com_newsfeeds/category/default_items.php</filename>
		<filename>html/com_newsfeeds/category/index.html</filename>
		<filename>html/com_newsfeeds/newsfeed/default.php</filename>
		<filename>html/com_newsfeeds/newsfeed/index.html</filename>
		<filename>html/com_newsfeeds/index.html</filename>
		<filename>html/com_weblinks/categories/default.php</filename>
		<filename>html/com_weblinks/categories/index.html</filename>
		<filename>html/com_weblinks/category/default.php</filename>
		<filename>html/com_weblinks/category/default_items.php</filename>
		<filename>html/com_weblinks/category/index.html</filename>
		<filename>html/com_weblinks/weblinks/form.php</filename>
		<filename>html/com_weblinks/weblinks/index.html</filename>
		<filename>html/com_weblinks/index.html</filename>
		<filename>html/com_user/login/index.html</filename>
		<filename>html/com_user/login/default_login.php</filename>
		<filename>html/com_user/login/default_logout.php</filename>
		<filename>html/com_user/register/default.php</filename>
		<filename>html/com_user/register/index.html</filename>
		<filename>html/com_user/register/default_message.php</filename>
		<filename>html/com_user/lostpass/default.php</filename>
		<filename>html/com_user/lostpass/index.html</filename>
		<filename>html/com_user/index.html</filename>
		<filename>images/arrow.png</filename>
		<filename>images/pfeil.gif</filename>
		<filename>images/trans.gif</filename>
		<filename>images/logo.gif</filename>
		<filename>images/arrow.gif</filename>
		<filename>images/biene.gif</filename>
		<filename>images/index.html</filename>
		<filename>images/con_address.png</filename>
		<filename>images/lupe_larger.gif</filename>
		<filename>images/lupe_larger_black.gif</filename>
		<filename>images/lupe_reset.gif</filename>
		<filename>images/lupe_reset_black.gif</filename>
		<filename>images/lupe_smaller.gif</filename>
		<filename>images/lupe_smaller_black.gif</filename>
		<filename>index.html</filename>
		<filename>index.php</filename>
		<filename>javascript/md_stylechanger.js</filename>
		<filename>javascript/index.html</filename>
		<filename>params.ini</filename>
		<filename>templateDetails.xml</filename>
		<filename>template_thumbnail.png</filename>
		<filename>todo.txt</filename>
	</files>
	<positions>
		<position>left</position>
		<position>right</position>
		<position>top</position>
		<position>breadcrumb</position>
		<position>user1</position>
		<position>user2</position>
		<position>user3</position>
		<position>user4</position>
		<position>debug</position>
		<position>syndicate</position>
	</positions>
	<params>
		<param name="headerLevelComponent" type="list" default="2"
			label="header level Component" description="">
			<option value="1">h1</option>
			<option value="2">h2</option>
			<option value="3">h3</option>
			<option value="4">h4</option>
			<option value="5">h5</option>
		</param>
		<param name="pageTitleHeaderLevel" type="list" default="1"
			label="header level page title" description="">
			<option value="1">h1</option>
			<option value="2">h2</option>
			<option value="3">h3</option>
			<option value="4">h4</option>
			<option value="5">h5</option>
		</param>
	</params>
</install>
